skyrunner/__init__.py
skyrunner/_direction/__init__.py
skyrunner/_driver/__init__.py
skyrunner/_enums/__init__.py
skyrunner/_enums/enum_meta.py
skyrunner/_enums/supported_actions.py
skyrunner/_enums/supported_browser.py
skyrunner/_enums/supported_driver.py
skyrunner/_enums/supported_script_lang.py
skyrunner/_enums/supported_selector_type.py
skyrunner/_model/__init__.py
skyrunner/_model/direction.py
skyrunner/_tasks/__init__.py
skyrunner/_tasks/base.py
skyrunner/_tasks/click.py
skyrunner/_tasks/custom.py
skyrunner/_tasks/enter.py
skyrunner/_tasks/input.py
skyrunner/_tasks/link.py
skyrunner/_tasks/shared_input.py
skyrunner/_tasks/task_manager.py
skyrunner-0.0.4.dist-info/METADATA
skyrunner-0.0.4.dist-info/RECORD
skyrunner-0.0.4.dist-info/WHEEL
skyrunner-0.0.4.dist-info/top_level.txt
