Metadata-Version: 2.1
Name: skyrunner
Version: 0.0.4
Summary: Skyrunner scrapes with json definition
Home-page: https://github.com/globallines-developers/skyrunner
Author: Yusuke Kobayashi
Author-email: yusuke.kobayashi@mileshare.jp
License: MIT
Platform: UNKNOWN
Classifier: Programming Language :: Python :: 3
Classifier: Programming Language :: Python :: 3.3
Classifier: Programming Language :: Python :: 3.4
Classifier: Programming Language :: Python :: 3.5
Classifier: Programming Language :: Python :: 3.6
Classifier: License :: OSI Approved :: MIT License
Requires-Dist: selenium
Requires-Dist: future
